openbioseq/__init__.py
openbioseq/version.py
openbioseq/.mim/tools/dist_extract.sh
openbioseq/.mim/tools/dist_test.sh
openbioseq/.mim/tools/dist_train.sh
openbioseq/.mim/tools/extract.py
openbioseq/.mim/tools/kill.sh
openbioseq/.mim/tools/single_train.sh
openbioseq/.mim/tools/srun_extract.sh
openbioseq/.mim/tools/srun_test.sh
openbioseq/.mim/tools/srun_train.sh
openbioseq/.mim/tools/test.py
openbioseq/.mim/tools/train.py
openbioseq/.mim/tools/analysis_tools/analyze_logs.py
openbioseq/.mim/tools/analysis_tools/analyze_seq_feat.py
openbioseq/.mim/tools/analysis_tools/count_parameters.py
openbioseq/.mim/tools/analysis_tools/get_flops.py
openbioseq/.mim/tools/analysis_tools/gradcam.py
openbioseq/.mim/tools/analysis_tools/print_config.py
openbioseq/.mim/tools/model_converters/extract_backbone_weights.py
openbioseq/.mim/tools/model_converters/extract_dir_weights.py
openbioseq/.mim/tools/model_converters/publish_model.py
openbioseq/.mim/tools/model_converters/timm2openmixup.py
openbioseq/.mim/tools/model_converters/upgrade_models.py
openbioseq/.mim/tools/prepare_data/convert_imagenet_subsets.py
openbioseq/.mim/tools/prepare_data/convert_inaturalist.py
openbioseq/.mim/tools/prepare_data/convert_subset.py
openbioseq/.mim/tools/prepare_data/create_voc_data_files.py
openbioseq/.mim/tools/prepare_data/create_voc_low_shot_challenge_samples.py
openbioseq/.mim/tools/prepare_data/prepare_voc07_cls.sh
openbioseq/.mim/tools/summary/find_automix_val_median.py
openbioseq/.mim/tools/summary/find_classification_val_3times_average.py
openbioseq/.mim/tools/summary/find_classification_val_max.py
openbioseq/.mim/tools/summary/find_classification_val_median.py
openbioseq/.mim/tools/summary/find_regression_val_3times_average.py
openbioseq/apis/__init__.py
openbioseq/apis/train.py
openbioseq/core/__init__.py
openbioseq/core/hooks/__init__.py
openbioseq/core/hooks/addtional_scheduler.py
openbioseq/core/hooks/builder.py
openbioseq/core/hooks/deepcluster_hook.py
openbioseq/core/hooks/ema_hook.py
OpenBioSeq-0.1.1.dist-info/LICENSE
OpenBioSeq-0.1.1.dist-info/METADATA
OpenBioSeq-0.1.1.dist-info/WHEEL
OpenBioSeq-0.1.1.dist-info/top_level.txt
OpenBioSeq-0.1.1.dist-info/RECORD
