Metadata-Version: 2.1
Name: OpenBioSeq
Version: 0.1.1
Summary: Open Bio-sequence Toolbox for Supervision and Self-Supervision Learning
Home-page: https://github.com/Westlake-AI/OpenBioSeq
Author: CAIRI Westlake University Contributors
Author-email: CAIRI Westlake University Contributors <lisiyuan@westlake.edu.com>
License: Apache License 2.0
Project-URL: Homepage, https://github.com/Westlake-AI/OpenBioSeq
Keywords: bio-sequence embedding,supervised and self-supervised learning
Classifier: Development Status :: 4 - Beta
Classifier: License :: OSI Approved :: Apache Software License
Classifier: Operating System :: OS Independent
Classifier: Programming Language :: Python :: 3
Classifier: Programming Language :: Python :: 3.5
Classifier: Programming Language :: Python :: 3.6
Classifier: Programming Language :: Python :: 3.7
Classifier: Programming Language :: Python :: 3.8
Classifier: Programming Language :: Python :: 3.9
License-File: LICENSE
Requires-Dist: faiss-gpu (==1.6.1)
Requires-Dist: future
Requires-Dist: matplotlib
Requires-Dist: mmcv-full (>=1.4.7)
Requires-Dist: numpy
Requires-Dist: packaging
Requires-Dist: pandas
Requires-Dist: scipy
Requires-Dist: six
Requires-Dist: terminaltables
Requires-Dist: sklearn
Requires-Dist: seaborn
Requires-Dist: tensorboard
Requires-Dist: transformers
Requires-Dist: timm
Requires-Dist: tqdm
Provides-Extra: all
Provides-Extra: mim
Requires-Dist: mmcls (>=0.21.0) ; extra == 'mim'
Requires-Dist: mmcv-full (>=1.4.7) ; extra == 'mim'
Requires-Dist: mmdet (>=2.16.0) ; extra == 'mim'
Requires-Dist: mmsegmentation (>=0.20.2) ; extra == 'mim'
Provides-Extra: tests
Requires-Dist: asynctest ; extra == 'tests'
Requires-Dist: codecov ; extra == 'tests'
Requires-Dist: flake8 ; extra == 'tests'
Requires-Dist: isort ; extra == 'tests'
Requires-Dist: pytest ; extra == 'tests'
Requires-Dist: pytest-cov ; extra == 'tests'
Requires-Dist: pytest-runner ; extra == 'tests'
Requires-Dist: xdoctest (>=0.10.0) ; extra == 'tests'
Requires-Dist: yapf ; extra == 'tests'
Requires-Dist: kwarray ; extra == 'tests'
